yesaide/__init__.py
yesaide/cli.py
yesaide/config.py
yesaide/database.py
yesaide/foreman.py
yesaide/jwt.py
yesaide/mapping.py
yesaide/period.py
yesaide/validation.py
yesaide/worker.py
yesaide-1.7.0.dist-info/LICENSE
yesaide-1.7.0.dist-info/METADATA
yesaide-1.7.0.dist-info/WHEEL
yesaide-1.7.0.dist-info/top_level.txt
yesaide-1.7.0.dist-info/RECORD
