Metadata-Version: 2.1
Name: yesaide
Version: 1.7.0
Summary: UNKNOWN
Home-page: UNKNOWN
Author: Ouihelp Tech
Author-email: tech@ouihelp.fr
License: MIT
Platform: UNKNOWN
Classifier: Development Status :: 3 - Alpha
Classifier: Intended Audience :: Developers
Classifier: License :: OSI Approved :: MIT License
Classifier: Operating System :: OS Independent
Classifier: Programming Language :: Python
Classifier: Programming Language :: Python :: 3
Classifier: Topic :: Software Development :: Libraries :: Python Modules
License-File: LICENSE
Requires-Dist: SQLAlchemy <1.5,>=1.3
Requires-Dist: voluptuous <0.12,>=0.10.5
Requires-Dist: jwcrypto <0.7,>=0.6
Requires-Dist: python-dateutil <3,>=2
